{
  "books": [
    {
      "title": "Atomic Habits",
      "author": "James Clear",
      "publisher": "Avery",
      "publishedDate": "2018-10-16",
      "email": "publisher@avery.com",
      "recommendedAge": 18,
      "description": "A practical guide to building good habits and breaking bad ones...",
      "id": "1"
    },
    {
      "id": "2",
      "title": "Rich Dad Poor Dad",
      "author": "Robert Kiyosaki",
      "publisher": "Plata Publishing",
      "publishedDate": "1997-04-01",
      "description": "A personal finance book about money, investing, and financial thinking.",
      "email": "info@plata.com",
      "recommendedAge": 16
    },
    {
      "id": "3",
      "title": "The Alchemist",
      "author": "Paulo Coelho",
      "publisher": "HarperOne",
      "publishedDate": "1988-01-01",
      "description": "A philosophical story about dreams, destiny, and finding your purpose.",
      "email": "contact@harperone.com",
      "recommendedAge": 15
    },
    {
      "title": "Mrityunjaya",
      "author": "Shivaji Sawant",
      "publisher": "Continental, Paperback",
      "publishedDate": "1967-01-01",
      "email": "abc@gmail.com",
      "recommendedAge": 60,
      "description": "Mrityunjay (Triumph Over Death) is a renowned Marathi novel by Shivaji Sawant based on the life of Karna, a central, tragic character from the Mahabharata. Written as an autobiography, the book explores Karna’s life, his struggle with casteism, loyalty to Duryodhana, and his philosophical battles, portraying him as a legendary \"winner over death\".....",
      "id": "I3T45OwZtUM"
    }
  ],
  "$schema": "./node_modules/json-server/schema.json"
}